{
  "_fv": 57,
  "_type": "recipe",
  "definition": {
    "recipeType": "Crafting",
    "recipeRetstackSize": 1,
    "group": "",
    "cookingBookCategory": "MISC",
    "xpReward": 0.0,
    "cookingTime": 200,
    "craftingBookCategory": "MISC",
    "recipeShapeless": false,
    "recipeSlots": [
      {
        "value": "Items.DYE#7"
      },
      {
        "value": "Items.DYE#7"
      },
      {
        "value": "Items.DYE#7"
      },
      {
        "value": "Items.DYE#7"
      },
      {
        "value": "TAG:minecraft:tag_egg"
      },
      {
        "value": "Items.DYE#7"
      },
      {
        "value": "Items.DYE#7"
      },
      {
        "value": "Items.DYE#7"
      },
      {
        "value": "Items.DYE#7"
      }
    ],
    "recipeReturnStack": {
      "value": "CUSTOM:LightGrayChiken"
    },
    "name": "r_light_gray_chiken",
    "namespace": "mod"
  }
}